FreezeUI/__init__.py
FreezeUI/__main__.py
FreezeUI/editor_window.py
FreezeUI/exe_win.py
FreezeUI/msi_win.py
FreezeUI/assets/exe_template.txt
FreezeUI/assets/exe_text.png
FreezeUI/assets/icon.gif
FreezeUI/assets/icon.ico
FreezeUI/assets/msi_template.txt
FreezeUI/assets/msi_text.png
FreezeUI/assets/pyicon.svg
FreezeUI_U/__init__.py
FreezeUI_U/__main__.py
FreezeUI_U/editor_window.py
FreezeUI_U/exe_win.py
FreezeUI_U/msi_win.py
FreezeUI_U/assets/exe_template.txt
FreezeUI_U/assets/exe_text.png
FreezeUI_U/assets/icon.gif
FreezeUI_U/assets/icon.ico
FreezeUI_U/assets/msi_template.txt
FreezeUI_U/assets/msi_text.png
FreezeUI_U/assets/pyicon.svg
FreezeUI_U-0.0.5.data/data/bitmaps/exe_text.png
FreezeUI_U-0.0.5.data/data/bitmaps/icon.gif
FreezeUI_U-0.0.5.data/data/bitmaps/icon.ico
FreezeUI_U-0.0.5.data/data/bitmaps/msi_text.png
FreezeUI_U-0.0.5.data/data/bitmaps/pyicon.svg
FreezeUI_U-0.0.5.data/data/text files/exe_template.txt
FreezeUI_U-0.0.5.data/data/text files/msi_template.txt
FreezeUI_U-0.0.5.dist-info/LICENSE
FreezeUI_U-0.0.5.dist-info/METADATA
FreezeUI_U-0.0.5.dist-info/WHEEL
FreezeUI_U-0.0.5.dist-info/entry_points.txt
FreezeUI_U-0.0.5.dist-info/top_level.txt
FreezeUI_U-0.0.5.dist-info/RECORD
