Metadata-Version: 2.1
Name: FreezeUI-U
Version: 0.0.5
Summary: This a GUI for converting python scripts to applications using cx_Freeze.
Home-page: https://akshatchauhan18.github.io/FreezeUI
Author: Akshat Chauhan
Author-email: coder.akshatch@gmail.com
License: GNU GPL v3
Keywords: python,gui,cx_Freeze,FreezeUI
Platform: UNKNOWN
Classifier: Intended Audience :: Developers
Classifier: Intended Audience :: Education
Classifier: License :: OSI Approved :: GNU General Public License v3 (GPLv3)
Classifier: Programming Language :: Python
Classifier: Programming Language :: Python :: 3
Classifier: Programming Language :: Python :: 3.6
Classifier: Programming Language :: Python :: 3.7
Classifier: Programming Language :: Python :: 3.8
Classifier: Programming Language :: Python :: 3.9
Classifier: Programming Language :: Python :: 3.10
Classifier: Operating System :: Microsoft :: Windows
License-File: LICENSE
Requires-Dist: PyQt6
Requires-Dist: cx-Freeze
Requires-Dist: python-version (<=3.6)
Requires-Dist: QtPy
Requires-Dist: qtconsole
Requires-Dist: pyqt6-qscintilla
Requires-Dist: plyer
Provides-Extra: dev
Requires-Dist: pytest (==6.2.4) ; extra == 'dev'
